commerce_coinbase/__init__.py
commerce_coinbase/api.py
commerce_coinbase-0.1.0.dist-info/LICENSE
commerce_coinbase-0.1.0.dist-info/METADATA
commerce_coinbase-0.1.0.dist-info/WHEEL
commerce_coinbase-0.1.0.dist-info/top_level.txt
commerce_coinbase-0.1.0.dist-info/RECORD
