Metadata-Version: 2.1
Name: commerce-coinbase
Version: 0.1.0
Summary: A simple unofficial Python wrapper for the Coinbase Commerce API.
Home-page: https://github.com/MaxieDev/commerce_coinbase
Author: MaxieDev
Author-email: support@trinixbot.xyz
License: UNKNOWN
Platform: UNKNOWN
Classifier: Programming Language :: Python :: 3
Classifier: License :: OSI Approved :: GNU General Public License v3 or later (GPLv3+)
Classifier: Operating System :: OS Independent
Requires-Python: >=3.9
Requires-Dist: httpx
